Workbook

Sheet Premium
A1: Irecon Insurance
A2: Premium Breakdown
A3: Generated | B3: 13 Aug 2026, 11:49 pm | C3: Spreadsheet version | D3: 1.4
A4: App version | B4: 1.0.0
A5: Policy number | B5: ATCCWI1116 | C5: Insured | D5: ATCCWI1116 Construction
A6: Cover type | B6: Annual | C6: Estimated turnover | D6: 1250000
A7: Site | B7: 123 Sydney Street, Sydney NSW 2000
A8: Amounts below are Excel formulas from Policy + Rates (not pasted totals).
A10: Component | B10: Contract works | C10: Legal liability | D10: Combined
A11: Base Premium | B11: =ROUND(Policy!$B$8*Rates!$B$3,2) -> 66587.5 | C11: =ROUND(Policy!$B$8*Rates!$B$5,2) -> 15432.09 | D11: =ROUND(SUM(B11:C11),2) -> 82019.59
A12: True Base Premium | B12: =ROUND(MAX(B11,Rates!$B$4),2) -> 66587.5 | C12: =ROUND(MAX(C11,Rates!$B$6),2) -> 15432.09 | D12: =ROUND(SUM(B12,C12,B13,B14,B15,B16,B17),2) -> 101177.65
A13: Terrorism Levy | B13: =ROUND(SUM(B12,B14,B15)*Rates!$B$12,2) -> 3552.18 | D13: =ROUND(B13,2) -> 3552.18
A14: Display Homes | B14: =ROUND(Policy!$B$13,2) -> 3312.5 | D14: =ROUND(B14,2) -> 3312.5
A15: Existing Structure | B15: =ROUND(Policy!$B$14,2) -> 4968.75 | D15: =ROUND(B15,2) -> 4968.75
A16: Plant and Equipment | B16: =ROUND(Policy!$B$10*Rates!$B$7,2) -> 6658.75 | D16: =ROUND(B16,2) -> 6658.75
A17: Terrorism Levy Plant and Equipment | B17: =ROUND(IF(B16>0,B16*Rates!$B$12,0),2) -> 665.88 | D17: =ROUND(B17,2) -> 665.88
A18: ESL Plant and Equipment | B18: =ROUND(IF(B16>0,SUM(B16,B17)*Rates!$B$9,0),2) -> 211.1 | D18: =ROUND(B18,2) -> 211.1
A19: ESL | B19: =ROUND(SUM(B12,B13,B14,B15)*Rates!$B$8,2) -> 2227.2 | C19: =ROUND(0,2) -> 308.64 | D19: =ROUND(SUM(B19,C19,B18),2) -> 2746.94
A20: GST | B20: =ROUND(SUM(B12:B19)*Rates!$B$14,2) -> 7236.69 | C20: =ROUND(SUM(C12,C19)*Rates!$B$14,2) -> 1574.07 | D20: =ROUND(SUM(B20:C20),2) -> 8810.76
A21: Stamp Duty | B21: =ROUND(SUM(B12:B20)*Rates!$B$10,2) -> 4011.5 | C21: =ROUND(SUM(C12,C19,C20)*Rates!$B$11,2) -> 842.5 | D21: =ROUND(SUM(B21:C21),2) -> 4854
A22: Broker Fee | D22: =ROUND(Policy!$B$15,2) -> 6658.75
A23: Total Premium | B23: =ROUND(SUM(B12:B21),2) -> 89198.32 | C23: =ROUND(SUM(C12,C19:C21),2) -> 18177.3 | D23: =ROUND(SUM(B23,C23,D22),2) -> 107375.62
A25: Plant premium uses rate × plant value (v2.1+). Open Policy / Rates to change drivers; Premium recalculates via formulas.

Sheet Policy
A1: Policy
A2: Field | B2: Value | C2: Notes
A3: Policy number | B3: ATCCWI1116
A4: Insured name | B4: ATCCWI1116 Construction
A5: Cover type | B5: Annual
A6: Certificate / start date | B6: 2024-01-01
A7: End date | B7: 2025-01-01
A8: Estimated turnover | B8: 1250000 | C8: Original / estimated turnover (bind)
A9: Contract works sum insured | B9: 625000
A10: Plant & equipment | B10: 125000
A11: Display homes (limits) | B11: 62500
A12: Existing structure (limits) | B12: 93750
A13: Display homes premium (manual) | B13: 3312.5 | C13: Broker-entered premium line (not rate-derived)
A14: Existing structure premium (manual) | B14: 4968.75 | C14: Broker-entered premium line (not rate-derived)
A15: Broker fee (incl. GST) | B15: 6658.75
A16: Liability limit | B16: $10 Million
A17: State | B17: NSW
A18: Postcode | B18: 2000
A19: Site address | B19: 123 Sydney Street, Sydney NSW 2000
A20: Adjustment turnover | B20: 1050000 | C20: End-of-term adjustment turnover
A21: Stamp duty exempt | B21: No | C21: Yes → Section 2 stamp duty is zero
A22: Bind CW true base premium | B22: 66587.5 | C22: Stored bind premium (adjust original)
A23: Bind CW terrorism levy | B23: 3552.18
A24: Bind LL true base premium | B24: 15432.09
A25: Bind CW ESL | B25: 2227.2
A26: Bind CW GST | B26: 7236.69
A27: Bind CW stamp duty | B27: 4011.5
A28: Bind LL ESL | B28: 308.64
A29: Bind LL GST | B29: 1574.07
A30: Bind LL stamp duty | B30: 842.5
A31: Bind CW base (calculated) | B31: 66587.5
A32: Bind LL base (calculated) | B32: 15432.09
A33: Bind CW plant | B33: 6658.75
A34: Bind CW plant terrorism | B34: 665.88
A35: Bind CW plant ESL | B35: 211.1

Sheet Rates
A1: Pricing rates
A2: Rate | B2: Value | C2: Source / notes
A3: Contract works applied rate | B3: 0.05327 | C3: price_* schedule
A4: Contract works min premium | B4: 31250 | C4: price_* schedule
A5: Liability applied rate | B5: 0.012346 | C5: price_* schedule
A6: Liability min premium | B6: 6250 | C6: price_* schedule
A7: Plant premium rate | B7: 0.053269 | C7: price_plant
A8: ESL rate (construction) | B8: 0.031754 | C8: price_esl
A9: Plant ESL rate | B9: 0.03175 | C9: price_esl
A10: Stamp duty rate (section 1) | B10: 0.046035 | C10: price_stamp_duty
A11: Stamp duty rate (section 2) | B11: 0.048658 | C11: price_stamp_duty
A12: Terrorism rate (τ) | B12: 0.053346 | C12: Tier 2
A13: Terrorism tier | B13: 2 | C13: Postcode / state lookup
A14: GST rate | B14: 0.1
A15: Plant value min | B15: 62500 | C15: price_plant
A16: Plant value max | B16: 625000 | C16: price_plant

Sheet Adjustment
A1: End-of-term adjustment
A2: Original Turnover | B2: =ROUND(Policy!$B$8,2) -> 1250000
A3: Adjustment Turnover | B3: =ROUND(Policy!$B$20,2) -> 1050000
A4: Stamp Duty Exempt | B4: =Policy!$B$21 -> No
A6: Frozen rates (same as app — 6 dp; amounts use ROUND to cents)
A7: CW applied rate | B7: 0.05327
A8: LL applied rate | B8: 0.012346
A9: CW min premium | B9: 31250
A10: LL min premium | B10: 6250
A11: Terrorism rate | B11: 0.053346
A12: ESL rate | B12: 0.031754
A13: CW stamp duty rate | B13: 0.046035
A14: LL stamp duty rate | B14: 0.048658
A15: GST rate | B15: 0.1
A17: Original
A18: Cover | B18: Total Premium | C18: True Base Premium | D18: Terrorism Levy | E18: ESL | F18: GST | G18: Stamp Duty
A19: Contract Works | B19: =ROUND(SUM(C19:G19),2) -> 83268.14 | C19: =ROUND(Policy!$B$22,2) -> 66587.5 | D19: =ROUND(Policy!$B$23,2) -> 3552.18 | E19: =ROUND(SUM(C19,D19)*Adjustment!$B$12,2) -> 2227.22 | F19: =ROUND(SUM(C19,D19,E19)*Adjustment!$B$15,2) -> 7236.69 | G19: =ROUND(SUM(C19,D19,E19,F19)*Adjustment!$B$13,2) -> 3664.55
A20: Legal Liability | B20: =ROUND(SUM(C20:G20),2) -> 18366.54 | C20: =ROUND(Policy!$B$24,2) -> 15432.09 | D20: =ROUND(0,2) -> 0 | E20: =ROUND(0,2) -> 490.03 | F20: =ROUND(SUM(C20,D20,E20)*Adjustment!$B$15,2) -> 1592.21 | G20: =ROUND(IF(UPPER(Adjustment!$B$4)="YES",0,SUM(C20,D20,E20,F20)*Adjustment!$B$14),2) -> 852.21
A21: TOTAL | B21: =ROUND(SUM(B19:B20),2) -> 101634.68 | C21: =ROUND(SUM(C19:C20),2) -> 82019.59 | D21: =ROUND(SUM(D19:D20),2) -> 3552.18 | E21: =ROUND(SUM(E19:E20),2) -> 2717.25 | F21: =ROUND(SUM(F19:F20),2) -> 8828.9 | G21: =ROUND(SUM(G19:G20),2) -> 4516.76
A23: Adjustment Turnover
A24: Cover | B24: Total Premium | C24: True Base Premium | D24: Terrorism Levy | E24: ESL | F24: GST | G24: Stamp Duty
A25: Contract Works | B25: =ROUND(SUM(C25:G25),2) -> 69945.23 | C25: =ROUND(MAX(Adjustment!$B$3*Adjustment!$B$7,Adjustment!$B$9),2) -> 55933.5 | D25: =ROUND(C25*Adjustment!$B$11,2) -> 2983.83 | E25: =ROUND(SUM(C25,D25)*Adjustment!$B$12,2) -> 1870.86 | F25: =ROUND(SUM(C25,D25,E25)*Adjustment!$B$15,2) -> 6078.82 | G25: =ROUND(SUM(C25,D25,E25,F25)*Adjustment!$B$13,2) -> 3078.22
A26: Legal Liability | B26: =ROUND(SUM(C26:G26),2) -> 15428.31 | C26: =ROUND(MAX(Adjustment!$B$3*Adjustment!$B$8,Adjustment!$B$10),2) -> 12963.3 | D26: =ROUND(0,2) -> 0 | E26: =ROUND(0,2) -> 411.64 | F26: =ROUND(SUM(C26,D26,E26)*Adjustment!$B$15,2) -> 1337.49 | G26: =ROUND(IF(UPPER(Adjustment!$B$4)="YES",0,SUM(C26,D26,E26,F26)*Adjustment!$B$14),2) -> 715.88
A27: TOTAL | B27: =ROUND(SUM(B25:B26),2) -> 85373.54 | C27: =ROUND(SUM(C25:C26),2) -> 68896.8 | D27: =ROUND(SUM(D25:D26),2) -> 2983.83 | E27: =ROUND(SUM(E25:E26),2) -> 2282.5 | F27: =ROUND(SUM(F25:F26),2) -> 7416.31 | G27: =ROUND(SUM(G25:G26),2) -> 3794.1
A29: Total Adjustment Premium
A30: Cover | B30: Total Premium | C30: True Base Premium | D30: Terrorism Levy | E30: ESL | F30: GST | G30: Stamp Duty
A31: Contract Works | B31: =ROUND(SUM(C31:G31),2) -> -13322.9 | C31: =ROUND(IF(AND(C25<C19,C19>0,(C19-C25)/C19>0.25),-C19*0.25,C25-C19),2) -> -10654 | D31: =ROUND(C31*Adjustment!$B$11,2) -> -568.35 | E31: =ROUND(SUM(C31,D31)*Adjustment!$B$12,2) -> -356.35 | F31: =ROUND(SUM(C31,D31,E31)*Adjustment!$B$15,2) -> -1157.87 | G31: =ROUND(SUM(C31,D31,E31,F31)*Adjustment!$B$13,2) -> -586.33
A32: Legal Liability | B32: =ROUND(SUM(C32:G32),2) -> -2938.23 | C32: =ROUND(IF(AND(C26<C20,C20>0,(C20-C26)/C20>0.25),-C20*0.25,C26-C20),2) -> -2468.79 | D32: =ROUND(0,2) -> 0 | E32: =ROUND(0,2) -> -78.39 | F32: =ROUND(SUM(C32,D32,E32)*Adjustment!$B$15,2) -> -254.72 | G32: =ROUND(IF(UPPER(Adjustment!$B$4)="YES",0,SUM(C32,D32,E32,F32)*Adjustment!$B$14),2) -> -136.33
A33: TOTAL | B33: =ROUND(SUM(B31:B32),2) -> -16261.13 | C33: =ROUND(SUM(C31:C32),2) -> -13122.79 | D33: =ROUND(SUM(D31:D32),2) -> -568.35 | E33: =ROUND(SUM(E31:E32),2) -> -434.74 | F33: =ROUND(SUM(F31:F32),2) -> -1412.59 | G33: =ROUND(SUM(G31:G32),2) -> -722.66
A35: All policies are subject to a minimum premium of 75% of original estimated premium paid
